tests/__init__.py
tests/mlogger.py
tests/core/__init__.py
tests/core/test_context.py
tests/core/test_graph.py
tests/core/test_module.py
tests/core/test_workspace.py
tests/utils/__init__.py
tests/utils/test_common.py
tests/utils/test_config.py
tests/utils/test_ddl.py
tests/utils/test_io.py
tests/utils/test_logs.py
v2v_toolkit/__init__.py
v2v_toolkit/exceptions.py
v2v_toolkit/core/__init__.py
v2v_toolkit/core/context.py
v2v_toolkit/core/graph.py
v2v_toolkit/core/module.py
v2v_toolkit/core/workspace.py
v2v_toolkit/tmp/__init__.py
v2v_toolkit/tmp/modules.py
v2v_toolkit/utils/__init__.py
v2v_toolkit/utils/common.py
v2v_toolkit/utils/config.py
v2v_toolkit/utils/dll.py
v2v_toolkit/utils/io.py
v2v_toolkit/utils/logs.py
v2v_toolkit-1.1.1.dist-info/LICENSE
v2v_toolkit-1.1.1.dist-info/METADATA
v2v_toolkit-1.1.1.dist-info/WHEEL
v2v_toolkit-1.1.1.dist-info/top_level.txt
v2v_toolkit-1.1.1.dist-info/RECORD
