Metadata-Version: 2.1
Name: v2v_toolkit
Version: 1.1.1
Summary: Ver2Vision-Toolkit: Unified interface for streamlining 'Verbal Data to Vision Synthesis with Latent Diffusion Models' project. Provides tools for managing low-level downstream tasks.
Home-page: https://github.com/lukaszmichalskii/ver2vision-toolkit
Author: Lukasz Michalski, Szymon Lopuszynski, Wojciech Rymer
Author-email: lukasz.michalski222@gmail.com
License: MIT
Classifier: License :: OSI Approved :: MIT License
Classifier: Programming Language :: Python :: 3
Classifier: Operating System :: OS Independent
Requires-Python: >=3.10
License-File: LICENSE
Requires-Dist: dask
Requires-Dist: networkx
Requires-Dist: PyYAML
Requires-Dist: setuptools
